skylab_genesis/__init__.py
skylab_genesis/version.py
skylab_genesis-1.0.0.dist-info/LICENSE
skylab_genesis-1.0.0.dist-info/METADATA
skylab_genesis-1.0.0.dist-info/WHEEL
skylab_genesis-1.0.0.dist-info/top_level.txt
skylab_genesis-1.0.0.dist-info/RECORD
