Metadata-Version: 2.1
Name: skylab-genesis
Version: 1.0.0
Summary: Skylab Genesis python client
Home-page: https://github.com/skylab-tech/genesis_client_python
Author: skylabtech
Author-email: info@skylabtech.ai
License: LICENSE.txt
Platform: UNKNOWN
Classifier: Programming Language :: Python :: 2
Classifier: Programming Language :: Python :: 2.7
Classifier: Programming Language :: Python :: 3
Classifier: Programming Language :: Python :: 3.4
Classifier: Programming Language :: Python :: 3.5
Classifier: License :: OSI Approved :: Apache Software License
Classifier: Development Status :: 5 - Production/Stable
Classifier: Topic :: Communications :: Email
Requires-Dist: requests (>=2.0.0)
Provides-Extra: test
Requires-Dist: pytest (>=3.0.5) ; extra == 'test'
Requires-Dist: pytest-cov (>=2.6.1) ; extra == 'test'
Requires-Dist: requests-mock (>=1.5.2) ; extra == 'test'
